boostaroota/__init__.py
boostaroota/boostaroota.py
boostaroota-1.3.dist-info/DESCRIPTION.rst
boostaroota-1.3.dist-info/METADATA
boostaroota-1.3.dist-info/RECORD
boostaroota-1.3.dist-info/WHEEL
boostaroota-1.3.dist-info/metadata.json
boostaroota-1.3.dist-info/top_level.txt
