Metadata-Version: 2.0
Name: boostaroota
Version: 1.3
Summary: A Fast XGBoost Feature Selection Algorithm
Home-page: http://github.com/chasedehan/BoostARoota
Author: Chase DeHan
Author-email: chasedehan@yahoo.com
License: MIT
Platform: UNKNOWN
Requires-Dist: numpy
Requires-Dist: pandas
Requires-Dist: xgboost
